{
  "@context": [
    "https://w3id.org/ro/crate/1.1/context",
    {
      "organism_classification": "https://schema.org/taxonomicRange",
      "BioChemEntity": "https://schema.org/BioChemEntity",
      "channel": "https://www.openmicroscopy.org/Schemas/Documentation/Generated/OME-2016-06/ome_xsd.html#Channel",
      "obo": "http://purl.obolibrary.org/obo/",
      "FBcv": "http://ontobee.org/ontology/FBcv/",
      "acquisiton_method": {
        "@reverse": "https://schema.org/result",
        "@type": "@id"
      },
      "biological_entity": "https://schema.org/about",
      "biosample": "http://purl.obolibrary.org/obo/OBI_0002648",
      "preparation_method": "https://www.wikidata.org/wiki/Property:P1537",
      "specimen": "http://purl.obolibrary.org/obo/HSO_0000308"
    }
  ],
  "@graph": [
    {
      "@id": "./",
      "@type": "Dataset",
      "license": "https://creativecommons.org/licenses/by/4.0/",
      "resultOf": {
        "@id": "#5a34ea92-3734-413e-ba2d-0ac93c4d0e14"
      }
    },
    {
      "@id": "ro-crate-metadata.json",
      "@type": "CreativeWork",
      "conformsTo": {
        "@id": "https://w3id.org/ro/crate/1.1"
      },
      "about": {
        "@id": "./"
      }
    },
    {
      "@id": "#c86921a1-89f8-4dce-925f-bc4821e52045",
      "@type": "biosample",
      "organism_classification": {
        "@id": "NCBI:txid10090"
      }
    },
    {
      "@id": "#381e57ce-2451-4758-bc95-6da8f3d8dd86",
      "@type": "specimen",
      "biosample": {
        "@id": "#c86921a1-89f8-4dce-925f-bc4821e52045"
      }
    },
    {
      "@id": "#5a34ea92-3734-413e-ba2d-0ac93c4d0e14",
      "@type": "image_acquisition",
      "fbbi_id": {
        "@id": "obo:FBbi_00000243"
      },
      "specimen": {
        "@id": "#381e57ce-2451-4758-bc95-6da8f3d8dd86"
      }
    }
  ]
}