{
  "@context": [
    "https://w3id.org/ro/crate/1.1/context",
    {
      "organism_classification": "https://schema.org/taxonomicRange",
      "BioChemEntity": "https://schema.org/BioChemEntity",
      "channel": "https://www.openmicroscopy.org/Schemas/Documentation/Generated/OME-2016-06/ome_xsd.html#Channel",
      "obo": "http://purl.obolibrary.org/obo/",
      "FBcv": "http://ontobee.org/ontology/FBcv/",
      "acquisiton_method": {
        "@reverse": "https://schema.org/result",
        "@type": "@id"
      },
      "biological_entity": "https://schema.org/about",
      "biosample": "http://purl.obolibrary.org/obo/OBI_0002648",
      "preparation_method": "https://www.wikidata.org/wiki/Property:P1537",
      "specimen": "http://purl.obolibrary.org/obo/HSO_0000308"
    }
  ],
  "@graph": [
    {
      "@id": "./",
      "@type": "Dataset",
      "license": "https://creativecommons.org/licenses/by/4.0/",
      "resultOf": {
        "@id": "#0e41683a-6ae6-48e2-950d-4a3031a07fd0"
      }
    },
    {
      "@id": "ro-crate-metadata.json",
      "@type": "CreativeWork",
      "conformsTo": {
        "@id": "https://w3id.org/ro/crate/1.1"
      },
      "about": {
        "@id": "./"
      }
    },
    {
      "@id": "#1c48177f-920a-4c4e-aa5a-9e4b87623f71",
      "@type": "biosample",
      "organism_classification": {
        "@id": "NCBI:txid10090"
      }
    },
    {
      "@id": "#38943c87-ea8c-4bd3-ab88-e4d2c1bbb464",
      "@type": "specimen",
      "biosample": {
        "@id": "#1c48177f-920a-4c4e-aa5a-9e4b87623f71"
      }
    },
    {
      "@id": "#0e41683a-6ae6-48e2-950d-4a3031a07fd0",
      "@type": "image_acquisition",
      "fbbi_id": {
        "@id": "obo:FBbi_00000243"
      },
      "specimen": {
        "@id": "#38943c87-ea8c-4bd3-ab88-e4d2c1bbb464"
      }
    }
  ]
}