{
  "@context": [
    "https://w3id.org/ro/crate/1.1/context",
    {
      "organism_classification": "https://schema.org/taxonomicRange",
      "BioChemEntity": "https://schema.org/BioChemEntity",
      "channel": "https://www.openmicroscopy.org/Schemas/Documentation/Generated/OME-2016-06/ome_xsd.html#Channel",
      "obo": "http://purl.obolibrary.org/obo/",
      "FBcv": "http://ontobee.org/ontology/FBcv/",
      "acquisiton_method": {
        "@reverse": "https://schema.org/result",
        "@type": "@id"
      },
      "biological_entity": "https://schema.org/about",
      "biosample": "http://purl.obolibrary.org/obo/OBI_0002648",
      "preparation_method": "https://www.wikidata.org/wiki/Property:P1537",
      "specimen": "http://purl.obolibrary.org/obo/HSO_0000308"
    }
  ],
  "@graph": [
    {
      "@id": "./",
      "@type": "Dataset",
      "license": "https://creativecommons.org/licenses/by/4.0/",
      "resultOf": {
        "@id": "#799ca40b-4c95-474e-a3af-8197c45ce600"
      }
    },
    {
      "@id": "ro-crate-metadata.json",
      "@type": "CreativeWork",
      "conformsTo": {
        "@id": "https://w3id.org/ro/crate/1.1"
      },
      "about": {
        "@id": "./"
      }
    },
    {
      "@id": "#bdefd13d-647b-4564-9141-944e8118ef5b",
      "@type": "biosample",
      "organism_classification": {
        "@id": "NCBI:txid10090"
      }
    },
    {
      "@id": "#39fa3489-801b-4622-89ff-03dfc3afe7e2",
      "@type": "specimen",
      "biosample": {
        "@id": "#bdefd13d-647b-4564-9141-944e8118ef5b"
      }
    },
    {
      "@id": "#799ca40b-4c95-474e-a3af-8197c45ce600",
      "@type": "image_acquisition",
      "fbbi_id": {
        "@id": "obo:FBbi_00000243"
      },
      "specimen": {
        "@id": "#39fa3489-801b-4622-89ff-03dfc3afe7e2"
      }
    }
  ]
}