{
  "@context": [
    "https://w3id.org/ro/crate/1.1/context",
    {
      "organism_classification": "https://schema.org/taxonomicRange",
      "BioChemEntity": "https://schema.org/BioChemEntity",
      "channel": "https://www.openmicroscopy.org/Schemas/Documentation/Generated/OME-2016-06/ome_xsd.html#Channel",
      "obo": "http://purl.obolibrary.org/obo/",
      "FBcv": "http://ontobee.org/ontology/FBcv/",
      "acquisiton_method": {
        "@reverse": "https://schema.org/result",
        "@type": "@id"
      },
      "biological_entity": "https://schema.org/about",
      "biosample": "http://purl.obolibrary.org/obo/OBI_0002648",
      "preparation_method": "https://www.wikidata.org/wiki/Property:P1537",
      "specimen": "http://purl.obolibrary.org/obo/HSO_0000308"
    }
  ],
  "@graph": [
    {
      "@id": "./",
      "@type": "Dataset",
      "license": "https://creativecommons.org/licenses/by/4.0/",
      "resultOf": {
        "@id": "#14ae9f12-bfad-4939-ac06-6fb34b0ecf5a"
      }
    },
    {
      "@id": "ro-crate-metadata.json",
      "@type": "CreativeWork",
      "conformsTo": {
        "@id": "https://w3id.org/ro/crate/1.1"
      },
      "about": {
        "@id": "./"
      }
    },
    {
      "@id": "#b61d0c19-418b-468e-8470-f38b8786fb2f",
      "@type": "biosample",
      "organism_classification": {
        "@id": "NCBI:txid10090"
      }
    },
    {
      "@id": "#7e9cc1b8-1dd1-404c-8454-ff7529adf83c",
      "@type": "specimen",
      "biosample": {
        "@id": "#b61d0c19-418b-468e-8470-f38b8786fb2f"
      }
    },
    {
      "@id": "#14ae9f12-bfad-4939-ac06-6fb34b0ecf5a",
      "@type": "image_acquisition",
      "fbbi_id": {
        "@id": "obo:FBbi_00000243"
      },
      "specimen": {
        "@id": "#7e9cc1b8-1dd1-404c-8454-ff7529adf83c"
      }
    }
  ]
}