{
  "@context": [
    "https://w3id.org/ro/crate/1.1/context",
    {
      "organism_classification": "https://schema.org/taxonomicRange",
      "BioChemEntity": "https://schema.org/BioChemEntity",
      "channel": "https://www.openmicroscopy.org/Schemas/Documentation/Generated/OME-2016-06/ome_xsd.html#Channel",
      "obo": "http://purl.obolibrary.org/obo/",
      "FBcv": "http://ontobee.org/ontology/FBcv/",
      "acquisiton_method": {
        "@reverse": "https://schema.org/result",
        "@type": "@id"
      },
      "biological_entity": "https://schema.org/about",
      "biosample": "http://purl.obolibrary.org/obo/OBI_0002648",
      "preparation_method": "https://www.wikidata.org/wiki/Property:P1537",
      "specimen": "http://purl.obolibrary.org/obo/HSO_0000308"
    }
  ],
  "@graph": [
    {
      "@id": "./",
      "@type": "Dataset",
      "license": "https://creativecommons.org/licenses/by/4.0/",
      "resultOf": {
        "@id": "#9054d161-2d8f-4771-ad03-721c816de832"
      }
    },
    {
      "@id": "ro-crate-metadata.json",
      "@type": "CreativeWork",
      "conformsTo": {
        "@id": "https://w3id.org/ro/crate/1.1"
      },
      "about": {
        "@id": "./"
      }
    },
    {
      "@id": "#62ec05f7-71b5-4367-9a12-ee2f832e2af2",
      "@type": "biosample",
      "organism_classification": {
        "@id": "NCBI:txid10090"
      }
    },
    {
      "@id": "#bebf67d5-4697-43da-976a-229861f57f99",
      "@type": "specimen",
      "biosample": {
        "@id": "#62ec05f7-71b5-4367-9a12-ee2f832e2af2"
      }
    },
    {
      "@id": "#9054d161-2d8f-4771-ad03-721c816de832",
      "@type": "image_acquisition",
      "fbbi_id": {
        "@id": "obo:FBbi_00000243"
      },
      "specimen": {
        "@id": "#bebf67d5-4697-43da-976a-229861f57f99"
      }
    }
  ]
}